torch_helpers/__init__.py
torch_helpers/torch_helper_test.py
torch_helpers/torch_helpers.py
torch_helpers-0.4.6.dist-info/METADATA
torch_helpers-0.4.6.dist-info/RECORD
torch_helpers-0.4.6.dist-info/WHEEL
torch_helpers-0.4.6.dist-info/top_level.txt
